jsonresume_to_rendercv/__init__.py
jsonresume_to_rendercv/converter.py
jsonresume_to_rendercv/validator.py
jsonresume_to_rendercv-0.1.0.dist-info/LICENSE
jsonresume_to_rendercv-0.1.0.dist-info/METADATA
jsonresume_to_rendercv-0.1.0.dist-info/WHEEL
jsonresume_to_rendercv-0.1.0.dist-info/entry_points.txt
jsonresume_to_rendercv-0.1.0.dist-info/top_level.txt
jsonresume_to_rendercv-0.1.0.dist-info/RECORD
