Metadata-Version: 2.1
Name: jsonresume-to-rendercv
Version: 0.1.0
Summary: A CLI tool to convert JSON Resume schema to RenderCV schema
Home-page: https://github.com/guruor/jsonresume-to-rendercv
Author: Govind Singh
Author-email: connect.govinds@gmail.com
License: UNKNOWN
Platform: UNKNOWN
Classifier: Programming Language :: Python :: 3
Classifier: License :: OSI Approved :: MIT License
Classifier: Operating System :: OS Independent
Requires-Python: >=3.6
License-File: LICENSE
Requires-Dist: jsonschema
Requires-Dist: requests
Requires-Dist: pyyaml
Provides-Extra: dev
Requires-Dist: pytest; extra == "dev"
Requires-Dist: twine; extra == "dev"
